face_recons/__init__.py
face_recons/main.py
face_recons/test.py
face_recons/train.py
face_recons-0.0.1.dist-info/LICENSE
face_recons-0.0.1.dist-info/METADATA
face_recons-0.0.1.dist-info/WHEEL
face_recons-0.0.1.dist-info/top_level.txt
face_recons-0.0.1.dist-info/RECORD
