Metadata-Version: 2.1
Name: face-recons
Version: 0.0.1
Summary: Face Reconstruction Applicaton
Home-page: https://github.com/sg7801/face
Author: Srishti Guleria
Author-email: guleriasrishti01@gmail.com
License: UNKNOWN
Platform: UNKNOWN
Classifier: Programming Language :: Python :: 3
Classifier: License :: OSI Approved :: MIT License
Classifier: Operating System :: OS Independent
Requires-Python: >=3.7
License-File: LICENSE
